LICENSE
MANIFEST.in
README.rst
VERSION
karma.conf.js
package.json
setup.py
casepropods/__init__.py
casepropods.family_connect_subscription.egg-info/PKG-INFO
casepropods.family_connect_subscription.egg-info/SOURCES.txt
casepropods.family_connect_subscription.egg-info/dependency_links.txt
casepropods.family_connect_subscription.egg-info/namespace_packages.txt
casepropods.family_connect_subscription.egg-info/not-zip-safe
casepropods.family_connect_subscription.egg-info/requires.txt
casepropods.family_connect_subscription.egg-info/top_level.txt
casepropods/family_connect_subscription/__init__.py
casepropods/family_connect_subscription/plugin.py
casepropods/family_connect_subscription/tests.py
casepropods/family_connect_subscription/karma/init.js
casepropods/family_connect_subscription/karma/main.js
casepropods/family_connect_subscription/karma/test-pod.coffee
casepropods/family_connect_subscription/karma/vendor/angular-mocks.js
casepropods/family_connect_subscription/karma/vendor/angular.min.js
casepropods/family_connect_subscription/static/subscription_pod.css
casepropods/family_connect_subscription/static/subscription_pod_directives.js
casepropods/family_connect_subscription/static/subscription_pod_template.html