Metadata-Version: 1.1
Name: casepropods.family-connect-subscription
Version: 0.3.4
Summary: FamilyConnect subscriptions data pod for casepro. Returns  case specific information about stage based messaging subscriptions.
Home-page: http://github.com/praekelt/casepropods.family_connect_subscription
Author: Praekelt Foundation
Author-email: dev@praekelt.com
License: BSD
Platform: UNKNOWN
Classifier: Programming Language :: Python
Classifier: Framework :: Django
Classifier: Topic :: Internet :: WWW/HTTP
Classifier: Topic :: Internet :: WWW/HTTP :: WSGI :: Application
